genesis_base/__init__.py
genesis_base/connections/__init__.py
genesis_base/connections/database.py
genesis_base/connections/mongodb.py
genesis_base/connections/s3.py
genesis_base/models/__init__.py
genesis_base/models/base.py
genesis_base/models/task.py
genesis_base/processor.py
genesis_base-0.1.2.dist-info/METADATA
genesis_base-0.1.2.dist-info/WHEEL
genesis_base-0.1.2.dist-info/RECORD
