Metadata-Version: 2.1
Name: genesis-base
Version: 0.1.2
Summary: Genesis video processing base package
Author: Genesis Team
Author-email: steven.ge@godscode.com.cn
Requires-Python: >=3.12,<4.0
Classifier: Programming Language :: Python :: 3
Classifier: Programming Language :: Python :: 3.12
Requires-Dist: boto3 (>=1.26.0,<2.0.0)
Requires-Dist: pydantic (>=2.0.0,<3.0.0)
Requires-Dist: pymongo (>=4.0.0,<5.0.0)
Requires-Dist: pymysql (>=1.0.0,<2.0.0)
Requires-Dist: sqlalchemy (>=1.4.0,<2.0.0)
